emiapi/__init__.py
emiapi/emiapi.py
emiapi/plotting.py
emiapi-0.2.0.dist-info/LICENSE
emiapi-0.2.0.dist-info/METADATA
emiapi-0.2.0.dist-info/WHEEL
emiapi-0.2.0.dist-info/RECORD
