Metadata-Version: 2.1
Name: emiapi
Version: 0.2.0
Summary: A python API client to interact with EMI API
Author: Jean Luchier
Author-email: jean.luchier@imageau.eu
Requires-Python: >=3.8,<4.0
Classifier: Programming Language :: Python :: 3
Classifier: Programming Language :: Python :: 3.8
Classifier: Programming Language :: Python :: 3.9
Classifier: Programming Language :: Python :: 3.10
Classifier: Programming Language :: Python :: 3.11
Requires-Dist: matplotlib (>=3.4.3,<4.0.0)
Requires-Dist: pandas (>=1.3.2,<2.0.0)
Requires-Dist: requests (>=2.26.0,<3.0.0)
